kuhl_haus/mdp/__init__.py
kuhl_haus/mdp/analyzers/__init__.py
kuhl_haus/mdp/analyzers/analyzer.py
kuhl_haus/mdp/analyzers/massive_data_analyzer.py
kuhl_haus/mdp/analyzers/top_stocks.py
kuhl_haus/mdp/components/__init__.py
kuhl_haus/mdp/components/market_data_cache.py
kuhl_haus/mdp/components/market_data_scanner.py
kuhl_haus/mdp/components/massive_data_listener.py
kuhl_haus/mdp/components/massive_data_processor.py
kuhl_haus/mdp/components/massive_data_queues.py
kuhl_haus/mdp/components/widget_data_service.py
kuhl_haus/mdp/data/__init__.py
kuhl_haus/mdp/data/market_data_analyzer_result.py
kuhl_haus/mdp/data/top_stocks_cache_item.py
kuhl_haus/mdp/enum/__init__.py
kuhl_haus/mdp/enum/constants.py
kuhl_haus/mdp/enum/market_data_cache_keys.py
kuhl_haus/mdp/enum/market_data_cache_ttl.py
kuhl_haus/mdp/enum/market_data_pubsub_keys.py
kuhl_haus/mdp/enum/market_data_scanner_names.py
kuhl_haus/mdp/enum/massive_data_queue.py
kuhl_haus/mdp/helpers/__init__.py
kuhl_haus/mdp/helpers/process_manager.py
kuhl_haus/mdp/helpers/queue_name_resolver.py
kuhl_haus/mdp/helpers/utils.py
kuhl_haus/mdp/helpers/web_socket_message_serde.py
kuhl_haus_mdp-0.1.16.dist-info/METADATA
kuhl_haus_mdp-0.1.16.dist-info/WHEEL
kuhl_haus_mdp-0.1.16.dist-info/entry_points.txt
kuhl_haus_mdp-0.1.16.dist-info/licenses/LICENSE.txt
kuhl_haus_mdp-0.1.16.dist-info/RECORD
