Metadata-Version: 2.1
Name: kuhl-haus-mdp
Version: 0.1.16
Summary: Market data processing pipeline for stock market scanner
Author-Email: Tom Pounders <git@oldschool.engineer>
License: The MIT License (MIT)
Classifier: Development Status :: 4 - Beta
Classifier: Programming Language :: Python
Project-URL: Homepage, https://github.com/kuhl-haus/kuhl-haus-mdp
Project-URL: Documentation, https://kuhl-haus-mdp.readthedocs.io
Project-URL: Source, https://github.com/kuhl-haus/kuhl-haus-mdp.git
Project-URL: Changelog, https://github.com/kuhl-haus/kuhl-haus-mdp/commits
Project-URL: Tracker, https://github.com/kuhl-haus/kuhl-haus-mdp/issues
Requires-Python: <3.13,>=3.9.21
Requires-Dist: aiohttp
Requires-Dist: aio-pika
Requires-Dist: fastapi
Requires-Dist: massive
Requires-Dist: pydantic-settings
Requires-Dist: python-dotenv
Requires-Dist: redis[asyncio]
Requires-Dist: tenacity
Requires-Dist: uvicorn[standard]
Requires-Dist: websockets
Provides-Extra: testing
Requires-Dist: setuptools; extra == "testing"
Requires-Dist: pdm-backend; extra == "testing"
Requires-Dist: pytest; extra == "testing"
Requires-Dist: pytest-cov; extra == "testing"
Requires-Dist: pytest-asyncio; extra == "testing"
